qqbot/__init__.py
qqbot/api.py
qqbot/async_api.py
qqbot/core/__init__.py
qqbot/core/exception/__init__.py
qqbot/core/exception/error.py
qqbot/core/network/__init__.py
qqbot/core/network/async_http.py
qqbot/core/network/http.py
qqbot/core/network/url.py
qqbot/core/network/ws/__init__.py
qqbot/core/network/ws/ws_event.py
qqbot/core/network/ws/ws_handler.py
qqbot/core/network/ws/ws_intents_handler.py
qqbot/core/network/ws/ws_session.py
qqbot/core/network/ws/dto/__init__.py
qqbot/core/network/ws/dto/enum_intents.py
qqbot/core/network/ws/dto/enum_opcode.py
qqbot/core/network/ws/dto/ws_payload.py
qqbot/core/network/ws_async/__init__.py
qqbot/core/network/ws_async/ws_async_client.py
qqbot/core/network/ws_async/ws_async_handler.py
qqbot/core/network/ws_async/ws_async_manager.py
qqbot/core/network/ws_async/ws_async_pool.py
qqbot/core/network/ws_sync/__init__.py
qqbot/core/network/ws_sync/ws_client.py
qqbot/core/network/ws_sync/ws_event_handler.py
qqbot/core/network/ws_sync/ws_session_manager.py
qqbot/core/network/ws_sync/ws_session_pool.py
qqbot/core/util/__init__.py
qqbot/core/util/json_util.py
qqbot/core/util/logging.py
qqbot/core/util/yaml_util.py
qqbot/model/__init__.py
qqbot/model/announce.py
qqbot/model/api_permission.py
qqbot/model/audio.py
qqbot/model/channel.py
qqbot/model/channel_permissions.py
qqbot/model/emoji.py
qqbot/model/guild.py
qqbot/model/guild_member.py
qqbot/model/guild_role.py
qqbot/model/inline_keyboard.py
qqbot/model/interaction.py
qqbot/model/member.py
qqbot/model/message.py
qqbot/model/mute.py
qqbot/model/pins_message.py
qqbot/model/reaction.py
qqbot/model/schedule.py
qqbot/model/token.py
qqbot/model/user.py
qqbot/model/ws_context.py
qq_bot-0.8.5.dist-info/LICENSE
qq_bot-0.8.5.dist-info/METADATA
qq_bot-0.8.5.dist-info/WHEEL
qq_bot-0.8.5.dist-info/top_level.txt
qq_bot-0.8.5.dist-info/RECORD
