Metadata-Version: 1.1
Name: qq-bot
Version: 0.8.5
Summary: qq guild robot sdk with python3, support asyncio and synchronous
Home-page: https://github.com/tencent-connect/botpy
Author: veehou
Author-email: veehou@tencent.com
License: Tencent
Platform: UNKNOWN
Classifier: Development Status :: 3 - Alpha
Classifier: Intended Audience :: Developers
Classifier: Topic :: Software Development
Classifier: License :: OSI Approved :: MIT License
Classifier: Programming Language :: Python :: 3.7
